<annotation>
	<folder></folder>
	<filename>large_-120-_jpg.rf.309d1f1435963f8d8f7543802e4452f2.jpg</filename>
	<path>large_-120-_jpg.rf.309d1f1435963f8d8f7543802e4452f2.jpg</path>
	<source>
		<database>roboflow.ai</database>
	</source>
	<size>
		<width>416</width>
		<height>416</height>
		<depth>3</depth>
	</size>
	<segmented>0</segmented>
	<object>
		<name>fire</name>
		<pose>Unspecified</pose>
		<truncated>0</truncated>
		<difficult>0</difficult>
		<occluded>0</occluded>
		<bndbox>
			<xmin>130</xmin>
			<xmax>271</xmax>
			<ymin>165</ymin>
			<ymax>322</ymax>
		</bndbox>
	</object>
	<object>
		<name>smoke</name>
		<pose>Unspecified</pose>
		<truncated>0</truncated>
		<difficult>0</difficult>
		<occluded>0</occluded>
		<bndbox>
			<xmin>173</xmin>
			<xmax>253</xmax>
			<ymin>50</ymin>
			<ymax>183</ymax>
		</bndbox>
	</object>
</annotation>
