<annotation>
	<folder></folder>
	<filename>large_-1176-_jpg.rf.c662fe4a650a2225aab6b7e67438c77e.jpg</filename>
	<path>large_-1176-_jpg.rf.c662fe4a650a2225aab6b7e67438c77e.jpg</path>
	<source>
		<database>roboflow.ai</database>
	</source>
	<size>
		<width>416</width>
		<height>416</height>
		<depth>3</depth>
	</size>
	<segmented>0</segmented>
	<object>
		<name>fire</name>
		<pose>Unspecified</pose>
		<truncated>0</truncated>
		<difficult>0</difficult>
		<occluded>0</occluded>
		<bndbox>
			<xmin>13</xmin>
			<xmax>411</xmax>
			<ymin>83</ymin>
			<ymax>409</ymax>
		</bndbox>
	</object>
	<object>
		<name>fire</name>
		<pose>Unspecified</pose>
		<truncated>0</truncated>
		<difficult>0</difficult>
		<occluded>0</occluded>
		<bndbox>
			<xmin>92</xmin>
			<xmax>288</xmax>
			<ymin>2</ymin>
			<ymax>79</ymax>
		</bndbox>
	</object>
</annotation>
