<annotation>
	<folder></folder>
	<filename>large_-254-_jpg.rf.88989f7a07de4bb5061fa9267f2432a6.jpg</filename>
	<path>large_-254-_jpg.rf.88989f7a07de4bb5061fa9267f2432a6.jpg</path>
	<source>
		<database>roboflow.ai</database>
	</source>
	<size>
		<width>416</width>
		<height>416</height>
		<depth>3</depth>
	</size>
	<segmented>0</segmented>
	<object>
		<name>fire</name>
		<pose>Unspecified</pose>
		<truncated>0</truncated>
		<difficult>0</difficult>
		<occluded>0</occluded>
		<bndbox>
			<xmin>31</xmin>
			<xmax>167</xmax>
			<ymin>174</ymin>
			<ymax>274</ymax>
		</bndbox>
	</object>
	<object>
		<name>fire</name>
		<pose>Unspecified</pose>
		<truncated>0</truncated>
		<difficult>0</difficult>
		<occluded>0</occluded>
		<bndbox>
			<xmin>172</xmin>
			<xmax>236</xmax>
			<ymin>270</ymin>
			<ymax>345</ymax>
		</bndbox>
	</object>
	<object>
		<name>fire</name>
		<pose>Unspecified</pose>
		<truncated>0</truncated>
		<difficult>0</difficult>
		<occluded>0</occluded>
		<bndbox>
			<xmin>241</xmin>
			<xmax>365</xmax>
			<ymin>300</ymin>
			<ymax>338</ymax>
		</bndbox>
	</object>
</annotation>
