<annotation>
	<folder></folder>
	<filename>large_-592-_jpg.rf.44026870e952120c6f9760c794e22b03.jpg</filename>
	<path>large_-592-_jpg.rf.44026870e952120c6f9760c794e22b03.jpg</path>
	<source>
		<database>roboflow.ai</database>
	</source>
	<size>
		<width>416</width>
		<height>416</height>
		<depth>3</depth>
	</size>
	<segmented>0</segmented>
	<object>
		<name>fire</name>
		<pose>Unspecified</pose>
		<truncated>0</truncated>
		<difficult>0</difficult>
		<occluded>0</occluded>
		<bndbox>
			<xmin>4</xmin>
			<xmax>261</xmax>
			<ymin>40</ymin>
			<ymax>410</ymax>
		</bndbox>
	</object>
</annotation>
