<annotation>
	<folder></folder>
	<filename>large_-20-_jpg.rf.6d5b6664de71f3d87ea29453c0a2a889.jpg</filename>
	<path>large_-20-_jpg.rf.6d5b6664de71f3d87ea29453c0a2a889.jpg</path>
	<source>
		<database>roboflow.ai</database>
	</source>
	<size>
		<width>416</width>
		<height>416</height>
		<depth>3</depth>
	</size>
	<segmented>0</segmented>
	<object>
		<name>fire</name>
		<pose>Unspecified</pose>
		<truncated>0</truncated>
		<difficult>0</difficult>
		<occluded>0</occluded>
		<bndbox>
			<xmin>12</xmin>
			<xmax>155</xmax>
			<ymin>102</ymin>
			<ymax>369</ymax>
		</bndbox>
	</object>
	<object>
		<name>fire</name>
		<pose>Unspecified</pose>
		<truncated>0</truncated>
		<difficult>0</difficult>
		<occluded>0</occluded>
		<bndbox>
			<xmin>154</xmin>
			<xmax>317</xmax>
			<ymin>33</ymin>
			<ymax>363</ymax>
		</bndbox>
	</object>
	<object>
		<name>fire</name>
		<pose>Unspecified</pose>
		<truncated>0</truncated>
		<difficult>0</difficult>
		<occluded>0</occluded>
		<bndbox>
			<xmin>305</xmin>
			<xmax>411</xmax>
			<ymin>84</ymin>
			<ymax>355</ymax>
		</bndbox>
	</object>
</annotation>
