<annotation>
	<folder></folder>
	<filename>large_-365-_jpg.rf.5f394e2b42325b0ba1eb472f888eca89.jpg</filename>
	<path>large_-365-_jpg.rf.5f394e2b42325b0ba1eb472f888eca89.jpg</path>
	<source>
		<database>roboflow.ai</database>
	</source>
	<size>
		<width>416</width>
		<height>416</height>
		<depth>3</depth>
	</size>
	<segmented>0</segmented>
	<object>
		<name>fire</name>
		<pose>Unspecified</pose>
		<truncated>0</truncated>
		<difficult>0</difficult>
		<occluded>0</occluded>
		<bndbox>
			<xmin>108</xmin>
			<xmax>219</xmax>
			<ymin>63</ymin>
			<ymax>179</ymax>
		</bndbox>
	</object>
	<object>
		<name>smoke</name>
		<pose>Unspecified</pose>
		<truncated>0</truncated>
		<difficult>0</difficult>
		<occluded>0</occluded>
		<bndbox>
			<xmin>15</xmin>
			<xmax>250</xmax>
			<ymin>6</ymin>
			<ymax>98</ymax>
		</bndbox>
	</object>
</annotation>
