<annotation>
	<folder></folder>
	<filename>large_-1697-_jpg.rf.9613aa59e5083bf6f9858c821c882b0c.jpg</filename>
	<path>large_-1697-_jpg.rf.9613aa59e5083bf6f9858c821c882b0c.jpg</path>
	<source>
		<database>roboflow.ai</database>
	</source>
	<size>
		<width>416</width>
		<height>416</height>
		<depth>3</depth>
	</size>
	<segmented>0</segmented>
	<object>
		<name>fire</name>
		<pose>Unspecified</pose>
		<truncated>0</truncated>
		<difficult>0</difficult>
		<occluded>0</occluded>
		<bndbox>
			<xmin>201</xmin>
			<xmax>413</xmax>
			<ymin>141</ymin>
			<ymax>337</ymax>
		</bndbox>
	</object>
	<object>
		<name>fire</name>
		<pose>Unspecified</pose>
		<truncated>0</truncated>
		<difficult>0</difficult>
		<occluded>0</occluded>
		<bndbox>
			<xmin>54</xmin>
			<xmax>204</xmax>
			<ymin>271</ymin>
			<ymax>315</ymax>
		</bndbox>
	</object>
	<object>
		<name>smoke</name>
		<pose>Unspecified</pose>
		<truncated>0</truncated>
		<difficult>0</difficult>
		<occluded>0</occluded>
		<bndbox>
			<xmin>41</xmin>
			<xmax>414</xmax>
			<ymin>3</ymin>
			<ymax>166</ymax>
		</bndbox>
	</object>
</annotation>
