<annotation>
	<folder></folder>
	<filename>large_-1074-_jpg.rf.3936c87ed93aa0ef97129300d3a1002f.jpg</filename>
	<path>large_-1074-_jpg.rf.3936c87ed93aa0ef97129300d3a1002f.jpg</path>
	<source>
		<database>roboflow.ai</database>
	</source>
	<size>
		<width>416</width>
		<height>416</height>
		<depth>3</depth>
	</size>
	<segmented>0</segmented>
	<object>
		<name>fire</name>
		<pose>Unspecified</pose>
		<truncated>0</truncated>
		<difficult>0</difficult>
		<occluded>0</occluded>
		<bndbox>
			<xmin>150</xmin>
			<xmax>297</xmax>
			<ymin>168</ymin>
			<ymax>283</ymax>
		</bndbox>
	</object>
	<object>
		<name>smoke</name>
		<pose>Unspecified</pose>
		<truncated>0</truncated>
		<difficult>0</difficult>
		<occluded>0</occluded>
		<bndbox>
			<xmin>180</xmin>
			<xmax>238</xmax>
			<ymin>5</ymin>
			<ymax>184</ymax>
		</bndbox>
	</object>
</annotation>
