<annotation>
	<folder></folder>
	<filename>large_-1849-_jpg.rf.df17f30626230b6f385f1fd99993edad.jpg</filename>
	<path>large_-1849-_jpg.rf.df17f30626230b6f385f1fd99993edad.jpg</path>
	<source>
		<database>roboflow.ai</database>
	</source>
	<size>
		<width>416</width>
		<height>416</height>
		<depth>3</depth>
	</size>
	<segmented>0</segmented>
	<object>
		<name>fire</name>
		<pose>Unspecified</pose>
		<truncated>0</truncated>
		<difficult>0</difficult>
		<occluded>0</occluded>
		<bndbox>
			<xmin>162</xmin>
			<xmax>308</xmax>
			<ymin>192</ymin>
			<ymax>301</ymax>
		</bndbox>
	</object>
	<object>
		<name>smoke</name>
		<pose>Unspecified</pose>
		<truncated>0</truncated>
		<difficult>0</difficult>
		<occluded>0</occluded>
		<bndbox>
			<xmin>141</xmin>
			<xmax>284</xmax>
			<ymin>24</ymin>
			<ymax>245</ymax>
		</bndbox>
	</object>
	<object>
		<name>other</name>
		<pose>Unspecified</pose>
		<truncated>0</truncated>
		<difficult>0</difficult>
		<occluded>0</occluded>
		<bndbox>
			<xmin>161</xmin>
			<xmax>259</xmax>
			<ymin>304</ymin>
			<ymax>376</ymax>
		</bndbox>
	</object>
</annotation>
