<annotation>
	<folder></folder>
	<filename>large_-2571-_jpg.rf.d97f0470e8a21634197661b716034686.jpg</filename>
	<path>large_-2571-_jpg.rf.d97f0470e8a21634197661b716034686.jpg</path>
	<source>
		<database>roboflow.ai</database>
	</source>
	<size>
		<width>416</width>
		<height>416</height>
		<depth>3</depth>
	</size>
	<segmented>0</segmented>
	<object>
		<name>fire</name>
		<pose>Unspecified</pose>
		<truncated>0</truncated>
		<difficult>0</difficult>
		<occluded>0</occluded>
		<bndbox>
			<xmin>211</xmin>
			<xmax>265</xmax>
			<ymin>57</ymin>
			<ymax>236</ymax>
		</bndbox>
	</object>
	<object>
		<name>fire</name>
		<pose>Unspecified</pose>
		<truncated>0</truncated>
		<difficult>0</difficult>
		<occluded>0</occluded>
		<bndbox>
			<xmin>219</xmin>
			<xmax>304</xmax>
			<ymin>295</ymin>
			<ymax>413</ymax>
		</bndbox>
	</object>
	<object>
		<name>smoke</name>
		<pose>Unspecified</pose>
		<truncated>0</truncated>
		<difficult>0</difficult>
		<occluded>0</occluded>
		<bndbox>
			<xmin>256</xmin>
			<xmax>413</xmax>
			<ymin>8</ymin>
			<ymax>410</ymax>
		</bndbox>
	</object>
	<object>
		<name>fire</name>
		<pose>Unspecified</pose>
		<truncated>0</truncated>
		<difficult>0</difficult>
		<occluded>0</occluded>
		<bndbox>
			<xmin>134</xmin>
			<xmax>158</xmax>
			<ymin>94</ymin>
			<ymax>142</ymax>
		</bndbox>
	</object>
	<object>
		<name>other</name>
		<pose>Unspecified</pose>
		<truncated>0</truncated>
		<difficult>0</difficult>
		<occluded>0</occluded>
		<bndbox>
			<xmin>17</xmin>
			<xmax>93</xmax>
			<ymin>94</ymin>
			<ymax>205</ymax>
		</bndbox>
	</object>
</annotation>
