<annotation>
	<folder></folder>
	<filename>large_-2687-_jpg.rf.82271f33123b37a27a7617aa2f67ef39.jpg</filename>
	<path>large_-2687-_jpg.rf.82271f33123b37a27a7617aa2f67ef39.jpg</path>
	<source>
		<database>roboflow.ai</database>
	</source>
	<size>
		<width>416</width>
		<height>416</height>
		<depth>3</depth>
	</size>
	<segmented>0</segmented>
	<object>
		<name>fire</name>
		<pose>Unspecified</pose>
		<truncated>0</truncated>
		<difficult>0</difficult>
		<occluded>0</occluded>
		<bndbox>
			<xmin>2</xmin>
			<xmax>416</xmax>
			<ymin>25</ymin>
			<ymax>232</ymax>
		</bndbox>
	</object>
</annotation>
