<annotation>
	<folder></folder>
	<filename>large_-962-_jpg.rf.60227f7d46a106db87467084d1c9fca9.jpg</filename>
	<path>large_-962-_jpg.rf.60227f7d46a106db87467084d1c9fca9.jpg</path>
	<source>
		<database>roboflow.ai</database>
	</source>
	<size>
		<width>416</width>
		<height>416</height>
		<depth>3</depth>
	</size>
	<segmented>0</segmented>
	<object>
		<name>fire</name>
		<pose>Unspecified</pose>
		<truncated>0</truncated>
		<difficult>0</difficult>
		<occluded>0</occluded>
		<bndbox>
			<xmin>205</xmin>
			<xmax>303</xmax>
			<ymin>250</ymin>
			<ymax>314</ymax>
		</bndbox>
	</object>
	<object>
		<name>smoke</name>
		<pose>Unspecified</pose>
		<truncated>0</truncated>
		<difficult>0</difficult>
		<occluded>0</occluded>
		<bndbox>
			<xmin>6</xmin>
			<xmax>235</xmax>
			<ymin>15</ymin>
			<ymax>282</ymax>
		</bndbox>
	</object>
</annotation>
