<annotation>
	<folder></folder>
	<filename>large_-1070-_jpg.rf.3fb9763e55054e7dbc5d74861d69584f.jpg</filename>
	<path>large_-1070-_jpg.rf.3fb9763e55054e7dbc5d74861d69584f.jpg</path>
	<source>
		<database>roboflow.ai</database>
	</source>
	<size>
		<width>416</width>
		<height>416</height>
		<depth>3</depth>
	</size>
	<segmented>0</segmented>
	<object>
		<name>fire</name>
		<pose>Unspecified</pose>
		<truncated>0</truncated>
		<difficult>0</difficult>
		<occluded>0</occluded>
		<bndbox>
			<xmin>238</xmin>
			<xmax>416</xmax>
			<ymin>7</ymin>
			<ymax>405</ymax>
		</bndbox>
	</object>
	<object>
		<name>fire</name>
		<pose>Unspecified</pose>
		<truncated>0</truncated>
		<difficult>0</difficult>
		<occluded>0</occluded>
		<bndbox>
			<xmin>2</xmin>
			<xmax>107</xmax>
			<ymin>77</ymin>
			<ymax>414</ymax>
		</bndbox>
	</object>
	<object>
		<name>fire</name>
		<pose>Unspecified</pose>
		<truncated>0</truncated>
		<difficult>0</difficult>
		<occluded>0</occluded>
		<bndbox>
			<xmin>145</xmin>
			<xmax>182</xmax>
			<ymin>17</ymin>
			<ymax>88</ymax>
		</bndbox>
	</object>
</annotation>
