<annotation>
	<folder></folder>
	<filename>middle_-3939-_jpg.rf.1670f7b16d9daf58c8447091fd31184d.jpg</filename>
	<path>middle_-3939-_jpg.rf.1670f7b16d9daf58c8447091fd31184d.jpg</path>
	<source>
		<database>roboflow.ai</database>
	</source>
	<size>
		<width>416</width>
		<height>416</height>
		<depth>3</depth>
	</size>
	<segmented>0</segmented>
	<object>
		<name>smoke</name>
		<pose>Unspecified</pose>
		<truncated>0</truncated>
		<difficult>0</difficult>
		<occluded>0</occluded>
		<bndbox>
			<xmin>110</xmin>
			<xmax>233</xmax>
			<ymin>3</ymin>
			<ymax>187</ymax>
		</bndbox>
	</object>
</annotation>
