<annotation>
	<folder></folder>
	<filename>middle_-3270-_jpg.rf.64c2d8197d8d27dbf954b5f992e26bc4.jpg</filename>
	<path>middle_-3270-_jpg.rf.64c2d8197d8d27dbf954b5f992e26bc4.jpg</path>
	<source>
		<database>roboflow.ai</database>
	</source>
	<size>
		<width>416</width>
		<height>416</height>
		<depth>3</depth>
	</size>
	<segmented>0</segmented>
	<object>
		<name>fire</name>
		<pose>Unspecified</pose>
		<truncated>0</truncated>
		<difficult>0</difficult>
		<occluded>0</occluded>
		<bndbox>
			<xmin>215</xmin>
			<xmax>255</xmax>
			<ymin>123</ymin>
			<ymax>211</ymax>
		</bndbox>
	</object>
	<object>
		<name>fire</name>
		<pose>Unspecified</pose>
		<truncated>0</truncated>
		<difficult>0</difficult>
		<occluded>0</occluded>
		<bndbox>
			<xmin>58</xmin>
			<xmax>115</xmax>
			<ymin>250</ymin>
			<ymax>353</ymax>
		</bndbox>
	</object>
</annotation>
