<annotation>
	<folder></folder>
	<filename>middle_-3783-_jpg.rf.b7be59625619d1d770e0928018686116.jpg</filename>
	<path>middle_-3783-_jpg.rf.b7be59625619d1d770e0928018686116.jpg</path>
	<source>
		<database>roboflow.ai</database>
	</source>
	<size>
		<width>416</width>
		<height>416</height>
		<depth>3</depth>
	</size>
	<segmented>0</segmented>
	<object>
		<name>fire</name>
		<pose>Unspecified</pose>
		<truncated>0</truncated>
		<difficult>0</difficult>
		<occluded>0</occluded>
		<bndbox>
			<xmin>193</xmin>
			<xmax>235</xmax>
			<ymin>205</ymin>
			<ymax>235</ymax>
		</bndbox>
	</object>
	<object>
		<name>fire</name>
		<pose>Unspecified</pose>
		<truncated>0</truncated>
		<difficult>0</difficult>
		<occluded>0</occluded>
		<bndbox>
			<xmin>238</xmin>
			<xmax>301</xmax>
			<ymin>107</ymin>
			<ymax>255</ymax>
		</bndbox>
	</object>
	<object>
		<name>fire</name>
		<pose>Unspecified</pose>
		<truncated>0</truncated>
		<difficult>0</difficult>
		<occluded>0</occluded>
		<bndbox>
			<xmin>276</xmin>
			<xmax>309</xmax>
			<ymin>5</ymin>
			<ymax>31</ymax>
		</bndbox>
	</object>
	<object>
		<name>smoke</name>
		<pose>Unspecified</pose>
		<truncated>0</truncated>
		<difficult>0</difficult>
		<occluded>0</occluded>
		<bndbox>
			<xmin>139</xmin>
			<xmax>234</xmax>
			<ymin>2</ymin>
			<ymax>197</ymax>
		</bndbox>
	</object>
	<object>
		<name>smoke</name>
		<pose>Unspecified</pose>
		<truncated>0</truncated>
		<difficult>0</difficult>
		<occluded>0</occluded>
		<bndbox>
			<xmin>242</xmin>
			<xmax>310</xmax>
			<ymin>5</ymin>
			<ymax>96</ymax>
		</bndbox>
	</object>
</annotation>
