<annotation>
	<folder></folder>
	<filename>middle_-3439-_jpg.rf.7530e0bc68d328135570600b12b5d9a4.jpg</filename>
	<path>middle_-3439-_jpg.rf.7530e0bc68d328135570600b12b5d9a4.jpg</path>
	<source>
		<database>roboflow.ai</database>
	</source>
	<size>
		<width>416</width>
		<height>416</height>
		<depth>3</depth>
	</size>
	<segmented>0</segmented>
	<object>
		<name>fire</name>
		<pose>Unspecified</pose>
		<truncated>0</truncated>
		<difficult>0</difficult>
		<occluded>0</occluded>
		<bndbox>
			<xmin>198</xmin>
			<xmax>303</xmax>
			<ymin>264</ymin>
			<ymax>375</ymax>
		</bndbox>
	</object>
	<object>
		<name>smoke</name>
		<pose>Unspecified</pose>
		<truncated>0</truncated>
		<difficult>0</difficult>
		<occluded>0</occluded>
		<bndbox>
			<xmin>189</xmin>
			<xmax>405</xmax>
			<ymin>65</ymin>
			<ymax>268</ymax>
		</bndbox>
	</object>
</annotation>
