<annotation>
	<folder></folder>
	<filename>middle_-131-_jpg.rf.5d5899efb895cbd064b4573c04f2a77d.jpg</filename>
	<path>middle_-131-_jpg.rf.5d5899efb895cbd064b4573c04f2a77d.jpg</path>
	<source>
		<database>roboflow.ai</database>
	</source>
	<size>
		<width>416</width>
		<height>416</height>
		<depth>3</depth>
	</size>
	<segmented>0</segmented>
	<object>
		<name>fire</name>
		<pose>Unspecified</pose>
		<truncated>0</truncated>
		<difficult>0</difficult>
		<occluded>0</occluded>
		<bndbox>
			<xmin>112</xmin>
			<xmax>136</xmax>
			<ymin>1</ymin>
			<ymax>29</ymax>
		</bndbox>
	</object>
	<object>
		<name>fire</name>
		<pose>Unspecified</pose>
		<truncated>0</truncated>
		<difficult>0</difficult>
		<occluded>0</occluded>
		<bndbox>
			<xmin>69</xmin>
			<xmax>225</xmax>
			<ymin>136</ymin>
			<ymax>411</ymax>
		</bndbox>
	</object>
</annotation>
