<annotation>
	<folder></folder>
	<filename>middle_-1218-_jpg.rf.3dc57d4ce0adaa80af233d7de6e58b34.jpg</filename>
	<path>middle_-1218-_jpg.rf.3dc57d4ce0adaa80af233d7de6e58b34.jpg</path>
	<source>
		<database>roboflow.ai</database>
	</source>
	<size>
		<width>416</width>
		<height>416</height>
		<depth>3</depth>
	</size>
	<segmented>0</segmented>
	<object>
		<name>fire</name>
		<pose>Unspecified</pose>
		<truncated>0</truncated>
		<difficult>0</difficult>
		<occluded>0</occluded>
		<bndbox>
			<xmin>105</xmin>
			<xmax>235</xmax>
			<ymin>38</ymin>
			<ymax>255</ymax>
		</bndbox>
	</object>
	<object>
		<name>fire</name>
		<pose>Unspecified</pose>
		<truncated>0</truncated>
		<difficult>0</difficult>
		<occluded>0</occluded>
		<bndbox>
			<xmin>235</xmin>
			<xmax>321</xmax>
			<ymin>135</ymin>
			<ymax>273</ymax>
		</bndbox>
	</object>
	<object>
		<name>smoke</name>
		<pose>Unspecified</pose>
		<truncated>0</truncated>
		<difficult>0</difficult>
		<occluded>0</occluded>
		<bndbox>
			<xmin>234</xmin>
			<xmax>406</xmax>
			<ymin>4</ymin>
			<ymax>129</ymax>
		</bndbox>
	</object>
	<object>
		<name>smoke</name>
		<pose>Unspecified</pose>
		<truncated>0</truncated>
		<difficult>0</difficult>
		<occluded>0</occluded>
		<bndbox>
			<xmin>329</xmin>
			<xmax>395</xmax>
			<ymin>143</ymin>
			<ymax>252</ymax>
		</bndbox>
	</object>
</annotation>
