<annotation>
	<folder></folder>
	<filename>middle_-3368-_jpg.rf.49e07cba986ccb097121c33f8f90007f.jpg</filename>
	<path>middle_-3368-_jpg.rf.49e07cba986ccb097121c33f8f90007f.jpg</path>
	<source>
		<database>roboflow.ai</database>
	</source>
	<size>
		<width>416</width>
		<height>416</height>
		<depth>3</depth>
	</size>
	<segmented>0</segmented>
	<object>
		<name>fire</name>
		<pose>Unspecified</pose>
		<truncated>0</truncated>
		<difficult>0</difficult>
		<occluded>0</occluded>
		<bndbox>
			<xmin>271</xmin>
			<xmax>360</xmax>
			<ymin>50</ymin>
			<ymax>168</ymax>
		</bndbox>
	</object>
	<object>
		<name>smoke</name>
		<pose>Unspecified</pose>
		<truncated>0</truncated>
		<difficult>0</difficult>
		<occluded>0</occluded>
		<bndbox>
			<xmin>232</xmin>
			<xmax>339</xmax>
			<ymin>23</ymin>
			<ymax>98</ymax>
		</bndbox>
	</object>
</annotation>
