<annotation>
	<folder></folder>
	<filename>middle_-1784-_jpg.rf.79a929ed827bed8e4882828499cb95d9.jpg</filename>
	<path>middle_-1784-_jpg.rf.79a929ed827bed8e4882828499cb95d9.jpg</path>
	<source>
		<database>roboflow.ai</database>
	</source>
	<size>
		<width>416</width>
		<height>416</height>
		<depth>3</depth>
	</size>
	<segmented>0</segmented>
	<object>
		<name>fire</name>
		<pose>Unspecified</pose>
		<truncated>0</truncated>
		<difficult>0</difficult>
		<occluded>0</occluded>
		<bndbox>
			<xmin>164</xmin>
			<xmax>177</xmax>
			<ymin>296</ymin>
			<ymax>319</ymax>
		</bndbox>
	</object>
	<object>
		<name>fire</name>
		<pose>Unspecified</pose>
		<truncated>0</truncated>
		<difficult>0</difficult>
		<occluded>0</occluded>
		<bndbox>
			<xmin>203</xmin>
			<xmax>236</xmax>
			<ymin>274</ymin>
			<ymax>322</ymax>
		</bndbox>
	</object>
	<object>
		<name>fire</name>
		<pose>Unspecified</pose>
		<truncated>0</truncated>
		<difficult>0</difficult>
		<occluded>0</occluded>
		<bndbox>
			<xmin>314</xmin>
			<xmax>350</xmax>
			<ymin>276</ymin>
			<ymax>324</ymax>
		</bndbox>
	</object>
	<object>
		<name>other</name>
		<pose>Unspecified</pose>
		<truncated>0</truncated>
		<difficult>0</difficult>
		<occluded>0</occluded>
		<bndbox>
			<xmin>101</xmin>
			<xmax>124</xmax>
			<ymin>246</ymin>
			<ymax>270</ymax>
		</bndbox>
	</object>
</annotation>
