<annotation>
	<folder></folder>
	<filename>other_-232-_jpg.rf.15182820624a940cadfa9c56c4006a3d.jpg</filename>
	<path>other_-232-_jpg.rf.15182820624a940cadfa9c56c4006a3d.jpg</path>
	<source>
		<database>roboflow.ai</database>
	</source>
	<size>
		<width>416</width>
		<height>416</height>
		<depth>3</depth>
	</size>
	<segmented>0</segmented>
	<object>
		<name>other</name>
		<pose>Unspecified</pose>
		<truncated>0</truncated>
		<difficult>0</difficult>
		<occluded>0</occluded>
		<bndbox>
			<xmin>294</xmin>
			<xmax>375</xmax>
			<ymin>136</ymin>
			<ymax>351</ymax>
		</bndbox>
	</object>
</annotation>
