<annotation>
	<folder></folder>
	<filename>other_-430-_jpg.rf.6c7962f7d0b8f4b94605928e6682a255.jpg</filename>
	<path>other_-430-_jpg.rf.6c7962f7d0b8f4b94605928e6682a255.jpg</path>
	<source>
		<database>roboflow.ai</database>
	</source>
	<size>
		<width>416</width>
		<height>416</height>
		<depth>3</depth>
	</size>
	<segmented>0</segmented>
	<object>
		<name>other</name>
		<pose>Unspecified</pose>
		<truncated>0</truncated>
		<difficult>0</difficult>
		<occluded>0</occluded>
		<bndbox>
			<xmin>167</xmin>
			<xmax>197</xmax>
			<ymin>181</ymin>
			<ymax>225</ymax>
		</bndbox>
	</object>
	<object>
		<name>other</name>
		<pose>Unspecified</pose>
		<truncated>0</truncated>
		<difficult>0</difficult>
		<occluded>0</occluded>
		<bndbox>
			<xmin>323</xmin>
			<xmax>349</xmax>
			<ymin>46</ymin>
			<ymax>87</ymax>
		</bndbox>
	</object>
</annotation>
